cookiecutter_python_package_demo/__init__.py
cookiecutter_python_package_demo/py.typed
cookiecutter_python_package_demo-0.1.0.dist-info/LICENSE
cookiecutter_python_package_demo-0.1.0.dist-info/WHEEL
cookiecutter_python_package_demo-0.1.0.dist-info/METADATA
cookiecutter_python_package_demo-0.1.0.dist-info/RECORD
