Metadata-Version: 2.1
Name: cookiecutter-python-package-demo
Version: 0.1.0
Summary: Demo of https://github.com/sgraaf/cookiecutter-python-package.
Keywords: 
Author-email: Steven van de Graaf <steven@vandegraaf.xyz>
Requires-Python: ~=3.8
Classifier: Development Status :: 4 - Beta
Classifier: License :: OSI Approved :: MIT License
Classifier: Programming Language :: Python
Classifier: Programming Language :: Python :: 3
Classifier: Programming Language :: Python :: 3.8
Classifier: Programming Language :: Python :: 3.9
Classifier: Programming Language :: Python :: 3.10
Classifier: Programming Language :: Python :: 3.11
Classifier: Programming Language :: Python :: 3.12
Classifier: Programming Language :: Python :: 3 :: Only
Classifier: Typing :: Typed
Requires-Dist: cookiecutter-python-package-demo[tests,docs] ; extra == "dev"
Requires-Dist: furo ; extra == "docs"
Requires-Dist: myst-parser ; extra == "docs"
Requires-Dist: sphinx ; extra == "docs"
Requires-Dist: sphinx-autobuild ; extra == "docs"
Requires-Dist: sphinx-copybutton ; extra == "docs"
Requires-Dist: sphinxext-opengraph ; extra == "docs"
Requires-Dist: pytest ; extra == "tests"
Project-URL: Changelog, https://cookiecutter-python-package-demo.readthedocs.io/en/stable/changelog.html
Project-URL: Documentation, https://cookiecutter-python-package-demo.readthedocs.io/en/stable/
Project-URL: Issue Tracker, https://github.com/sgraaf/cookiecutter-python-package-demo/issues
Project-URL: Source Code, https://github.com/sgraaf/cookiecutter-python-package-demo
Provides-Extra: dev
Provides-Extra: docs
Provides-Extra: tests
